rdkit_step/__init__.py
rdkit_step/_version.py
rdkit_step/metadata.py
rdkit_step/rdkit.py
rdkit_step/rdkit_parameters.py
rdkit_step/rdkit_step.py
rdkit_step/tk_rdkit.py
rdkit_step/data/references.bib
rdkit_step-2023.2.22.dist-info/AUTHORS.rst
rdkit_step-2023.2.22.dist-info/LICENSE
rdkit_step-2023.2.22.dist-info/METADATA
rdkit_step-2023.2.22.dist-info/WHEEL
rdkit_step-2023.2.22.dist-info/entry_points.txt
rdkit_step-2023.2.22.dist-info/top_level.txt
rdkit_step-2023.2.22.dist-info/zip-safe
rdkit_step-2023.2.22.dist-info/RECORD
