Metadata-Version: 2.1
Name: rdkit-step
Version: 2023.2.22
Summary: A SEAMM plugin for A SEAMM plug-in for RDKit
Home-page: https://github.com/molssi-seamm/rdkit_step
Author: Mohammad Mostafanejad
Author-email: sina.mostafanejad@gmail.com
License: BSD-3-Clause
Keywords: SEAMM,plug-in,flowchart
Platform: Linux
Platform: Mac OS-X
Platform: Unix
Platform: Windows
Classifier: Development Status :: 2 - Pre-Alpha
Classifier: Intended Audience :: Science/Research
Classifier: Topic :: Scientific/Engineering :: Chemistry
Classifier: Topic :: Scientific/Engineering :: Physics
Classifier: License :: OSI Approved :: BSD License
Classifier: Natural Language :: English
Classifier: Programming Language :: Python :: 3 :: Only
Classifier: Programming Language :: Python :: 3.7
Classifier: Programming Language :: Python :: 3.8
License-File: LICENSE
License-File: AUTHORS.rst
Requires-Dist: Pmw
Requires-Dist: seamm
Requires-Dist: seamm-util
Requires-Dist: seamm-widgets
